nengolib/__init__.py
nengolib/compat.py
nengolib/conftest.py
nengolib/connection.py
nengolib/learning.py
nengolib/monkeypatch.py
nengolib/network.py
nengolib/neurons.py
nengolib/processes.py
nengolib/solvers.py
nengolib/temporal.py
nengolib/testing.py
nengolib/version.py
nengolib/networks/__init__.py
nengolib/networks/echo_state.py
nengolib/networks/linear_network.py
nengolib/networks/reservoir.py
nengolib/networks/rolling_window.py
nengolib/networks/tests/__init__.py
nengolib/networks/tests/test_echo_state.py
nengolib/networks/tests/test_linear_network.py
nengolib/networks/tests/test_reservoir.py
nengolib/networks/tests/test_rolling_window.py
nengolib/signal/__init__.py
nengolib/signal/discrete.py
nengolib/signal/dists.py
nengolib/signal/learning.py
nengolib/signal/lyapunov.py
nengolib/signal/realizers.py
nengolib/signal/reduction.py
nengolib/signal/system.py
nengolib/signal/utils.py
nengolib/signal/tests/__init__.py
nengolib/signal/tests/test_discrete.py
nengolib/signal/tests/test_dists.py
nengolib/signal/tests/test_learning.py
nengolib/signal/tests/test_lyapunov.py
nengolib/signal/tests/test_realizers.py
nengolib/signal/tests/test_reduction.py
nengolib/signal/tests/test_system.py
nengolib/signal/tests/test_utils.py
nengolib/stats/__init__.py
nengolib/stats/_sobol_seq.py
nengolib/stats/leech.py
nengolib/stats/ntmdists.py
nengolib/stats/ortho.py
nengolib/stats/tests/__init__.py
nengolib/stats/tests/test_leech.py
nengolib/stats/tests/test_ntmdists.py
nengolib/stats/tests/test_ortho.py
nengolib/synapses/__init__.py
nengolib/synapses/analog.py
nengolib/synapses/digital.py
nengolib/synapses/hetero_synapse.py
nengolib/synapses/mapping.py
nengolib/synapses/tests/__init__.py
nengolib/synapses/tests/test_analog.py
nengolib/synapses/tests/test_digital.py
nengolib/synapses/tests/test_hetero_synapse.py
nengolib/synapses/tests/test_mapping.py
nengolib/tests/__init__.py
nengolib/tests/test_connection.py
nengolib-0.5.2.dist-info/DESCRIPTION.rst
nengolib-0.5.2.dist-info/METADATA
nengolib-0.5.2.dist-info/RECORD
nengolib-0.5.2.dist-info/WHEEL
nengolib-0.5.2.dist-info/metadata.json
nengolib-0.5.2.dist-info/top_level.txt
