Metadata-Version: 2.0
Name: nengolib
Version: 0.5.2
Summary: Tools for robust dynamics in Nengo
Home-page: https://github.com/arvoelke/nengolib/
Author: Aaron R. Voelker
Author-email: arvoelke@gmail.com
License: Free for non-commercial use (see Nengo license)
Download-URL: https://github.com/arvoelke/nengolib/archive/v0.5.2.tar.gz
Keywords: Neural Engineering Framework,Nengo,Dynamical Spiking Networks,Neural Dynamics,Reservoir Computing
Platform: UNKNOWN
Classifier: Development Status :: 5 - Production/Stable
Classifier: Framework :: Nengo
Classifier: Intended Audience :: Science/Research
Classifier: License :: Free for non-commercial use
Classifier: Operating System :: OS Independent
Classifier: Programming Language :: Python :: 2.7
Classifier: Programming Language :: Python :: 3.4
Classifier: Programming Language :: Python :: 3.5
Classifier: Programming Language :: Python :: 3.6
Classifier: Topic :: Scientific/Engineering :: Artificial Intelligence
Requires-Dist: nengo (<3.0,>=2.2.0)
Requires-Dist: numpy (>=1.13)
Requires-Dist: scipy (>=0.19.0)
